[
  {
    "identifier": 1525338740923,
    "value": "AI and Automation",
    "type": "Track",
    "children": [

    ],
    "parent": [
      1525338740922
    ]
  },
  {
    "identifier": 1525338740924,
    "value": "Big Data and Analytics",
    "type": "Track",
    "children": [

    ],
    "parent": [
      1525338740922
    ]
  },
  {
    "identifier": 1525338740927,
    "value": "ClS",
    "type": "Track",
    "children": [

    ],
    "parent": [
      1525338740922
    ]
  },
  {
    "identifier": 1525338740928,
    "value": "DataScience",
    "type": "Track",
    "children": [

    ],
    "parent": [
      1525338740922
    ]
  },
  {
    "identifier": 1525338740929,
    "value": "Digital",
    "type": "Track",
    "children": [

    ],
    "parent": [
      1525338740922
    ]
  },
  {
    "identifier": 1525338740930,
    "value": "Microsoft",
    "type": "Track",
    "children": [

    ],
    "parent": [
      1525338740922
    ]
  },
  {
    "identifier": 1525338740931,
    "value": "Java",
    "type": "Track",
    "children": [

    ],
    "parent": [
      1525338740922
    ]
  },
  {
    "identifier": 1525338740932,
    "value": "Mainframe",
    "type": "Track",
    "children": [

    ],
    "parent": [
      1525338740922
    ]
  },
  {
    "identifier": 1525338740933,
    "value": "UI",
    "type": "Track",
    "children": [

    ],
    "parent": [
      1525338740922
    ]
  },
  {
    "identifier": 1525338740934,
    "value": "IVS",
    "type": "Track",
    "children": [

    ],
    "parent": [
      1525338740922
    ]
  },
  {
    "identifier": 1525338740935,
    "value": "ORC",
    "type": "Track",
    "children": [

    ],
    "parent": [
      1525338740922
    ]
  },
  {
    "identifier": 1525338740936,
    "value": "SAP",
    "type": "Track",
    "children": [

    ],
    "parent": [
      1525338740922
    ]
  },
  {
    "identifier": 1525338740937,
    "value": "EAIS",
    "type": "Track",
    "children": [

    ],
    "parent": [
      1525338740922
    ]
  },
  {
    "identifier": 1525338740938,
    "value": "ECAS",
    "type": "Track",
    "children": [

    ],
    "parent": [
      1525338740922
    ]
  },
  {
    "identifier": 1525338740939,
    "value": "DNA",
    "type": "Track",
    "children": [

    ],
    "parent": [
      1525338740922
    ]
  },
  {
    "identifier": 1525338740940,
    "value": "DNA - Data Science",
    "type": "Track",
    "children": [

    ],
    "parent": [
      1525338740922
    ]
  },
  {
    "identifier": 1525338740941,
    "value": "DNA - Business Intelligence",
    "type": "Track",
    "children": [

    ],
    "parent": [
      1525338740922
    ]
  },
  {
    "identifier": 1525338740942,
    "value": "Mobility",
    "type": "Track",
    "children": [

    ],
    "parent": [
      1525338740922
    ]
  },
  {
    "identifier": 1525338740943,
    "value": "Agile",
    "type": "Track",
    "children": [

    ],
    "parent": [
      1525338740922
    ]
  },
  {
    "identifier": 1525338740944,
    "value": "Engineering",
    "type": "Track",
    "children": [

    ],
    "parent": [
      1525338740922
    ]
  },
  {
    "identifier": 1525338740945,
    "value": "Oracle",
    "type": "Track",
    "children": [

    ],
    "parent": [
      1525338740922
    ]
  },
  {
    "identifier": 1525338740946,
    "value": "open systems",
    "type": "Track",
    "children": [

    ],
    "parent": [
      1525338740922
    ]
  },
  {
    "identifier": 1525338740947,
    "value": "Databases",
    "type": "Track",
    "children": [

    ],
    "parent": [
      1525338740922
    ]
  },
  {
    "identifier": 1525338740948,
    "value": "Business Analysis",
    "type": "Track",
    "children": [

    ],
    "parent": [
      1525338740922
    ]
  },
  {
    "identifier": 1525338740949,
    "value": "AS400",
    "type": "Track",
    "children": [

    ],
    "parent": [
      1525338740922
    ]
  },
  {
    "identifier": 1525338740950,
    "value": "Cloud",
    "type": "Track",
    "children": [

    ],
    "parent": [
      1525338740922
    ]
  },
  {
    "identifier": 1525338740951,
    "value": "Security",
    "type": "Track",
    "children": [

    ],
    "parent": [
      1525338740922
    ]
  },
  {
    "identifier": 1525338740922,
    "value": "Technology",
    "type": "Category",
    "children": [
      1525338740923,
      1525338740924,
      1525338740927,
      1525338740928,
      1525338740929,
      1525338740930,
      1525338740931,
      1525338740932,
      1525338740933,
      1525338740934,
      1525338740935,
      1525338740936,
      1525338740937,
      1525338740938,
      1525338740939,
      1525338740940,
      1525338740941,
      1525338740942,
      1525338740943,
      1525338740944,
      1525338740945,
      1525338740946,
      1525338740947,
      1525338740948,
      1525338740949,
      1525338740950,
      1525338740951
    ],
    "parent": [
      1525338740921
    ]
  },
  {
    "identifier": 1525338740955,
    "value": "Infosys Service Lines",
    "type": "SubTrack",
    "children": [

    ],
    "parent": [
      1525338740954
    ]
  },
  {
    "identifier": 1525338740956,
    "value": "Infosys Products and Platforms",
    "type": "SubTrack",
    "children": [

    ],
    "parent": [
      1525338740954
    ]
  },
  {
    "identifier": 1525338740957,
    "value": "Tech Overview",
    "type": "SubTrack",
    "children": [

    ],
    "parent": [
      1525338740954
    ]
  },
  {
    "identifier": 1525338740958,
    "value": "Client/Industry",
    "type": "SubTrack",
    "children": [

    ],
    "parent": [
      1525338740954
    ]
  },
  {
    "identifier": 1525338740959,
    "value": "Competitors",
    "type": "SubTrack",
    "children": [

    ],
    "parent": [
      1525338740954
    ]
  },
  {
    "identifier": 1525338740960,
    "value": "Others",
    "type": "SubTrack",
    "children": [

    ],
    "parent": [
      1525338740954
    ]
  },
  {
    "identifier": 1525338740954,
    "value": "Primer",
    "type": "Track",
    "children": [
      1525338740955,
      1525338740956,
      1525338740957,
      1525338740958,
      1525338740959,
      1525338740960
    ],
    "parent": [
      1525338740953
    ]
  },
  {
    "identifier": 1525338740962,
    "value": "Elevator Pitch",
    "type": "SubTrack",
    "children": [

    ],
    "parent": [
      1525338740961
    ]
  },
  {
    "identifier": 1525338740963,
    "value": "Infosys Differentiators",
    "type": "SubTrack",
    "children": [

    ],
    "parent": [
      1525338740961
    ]
  },
  {
    "identifier": 1525338740964,
    "value": "Others",
    "type": "SubTrack",
    "children": [

    ],
    "parent": [
      1525338740961
    ]
  },
  {
    "identifier": 1525338740961,
    "value": "Sales Play",
    "type": "Track",
    "children": [
      1525338740962,
      1525338740963,
      1525338740964
    ],
    "parent": [
      1525338740953
    ]
  },
  {
    "identifier": 1525338740966,
    "value": "Value Stories",
    "type": "SubTrack",
    "children": [

    ],
    "parent": [
      1525338740965
    ]
  },
  {
    "identifier": 1525338740967,
    "value": "Case Studies",
    "type": "SubTrack",
    "children": [

    ],
    "parent": [
      1525338740965
    ]
  },
  {
    "identifier": 1525338740965,
    "value": "Credentials",
    "type": "Track",
    "children": [
      1525338740966,
      1525338740967
    ],
    "parent": [
      1525338740953
    ]
  },
  {
    "identifier": 1525338740969,
    "value": "Technical",
    "type": "SubTrack",
    "children": [

    ],
    "parent": [
      1525338740968
    ]
  },
  {
    "identifier": 1525338740970,
    "value": "Industry",
    "type": "SubTrack",
    "children": [

    ],
    "parent": [
      1525338740968
    ]
  },
  {
    "identifier": 1525338740968,
    "value": "Point of View",
    "type": "Track",
    "children": [
      1525338740969,
      1525338740970
    ],
    "parent": [
      1525338740953
    ]
  },
  {
    "identifier": 1525338740971,
    "value": "Sales Competencies",
    "type": "Track",
    "children": [

    ],
    "parent": [
      1525338740953
    ]
  },
  {
    "identifier": 1525338740953,
    "value": "Sales",
    "type": "Category",
    "children": [
      1525338740954,
      1525338740961,
      1525338740965,
      1525338740968,
      1525338740971
    ],
    "parent": [
      1525338740921
    ]
  },
  {
    "identifier": 1525338740973,
    "value": "Process",
    "type": "Track",
    "children": [

    ],
    "parent": [
      1525338740972
    ]
  },
  {
    "identifier": 1525338740972,
    "value": "Process",
    "type": "Category",
    "children": [
      1525338740973
    ],
    "parent": [
      1525338740921
    ]
  },
  {
    "identifier": 1525757739683,
    "value": "Banking Industry Insights",
    "type": "SubSubTrack",
    "children": [

    ],
    "parent": [
      1525757739682
    ]
  },
  {
    "identifier": 1525757739684,
    "value": "Consumer Banking",
    "type": "SubSubTrack",
    "children": [

    ],
    "parent": [
      1525757739682
    ]
  },
  {
    "identifier": 1525757739685,
    "value": "Commercial Banking",
    "type": "SubSubTrack",
    "children": [

    ],
    "parent": [
      1525757739682
    ]
  },
  {
    "identifier": 1525757739682,
    "value": "Banking",
    "type": "SubTrack",
    "children": [
      1525757739683,
      1525757739684,
      1525757739685
    ],
    "parent": [
      1525757739681
    ]
  },
  {
    "identifier": 1525757739687,
    "value": "Capital Markets Industry Insights",
    "type": "SubSubTrack",
    "children": [

    ],
    "parent": [
      1525757739686
    ]
  },
  {
    "identifier": 1525757739688,
    "value": "Front Office",
    "type": "SubSubTrack",
    "children": [

    ],
    "parent": [
      1525757739686
    ]
  },
  {
    "identifier": 1525757739689,
    "value": "Middle Office",
    "type": "SubSubTrack",
    "children": [

    ],
    "parent": [
      1525757739686
    ]
  },
  {
    "identifier": 1525757739690,
    "value": "Back Office",
    "type": "SubSubTrack",
    "children": [

    ],
    "parent": [
      1525757739686
    ]
  },
  {
    "identifier": 1525757739691,
    "value": "Corporate Function",
    "type": "SubSubTrack",
    "children": [

    ],
    "parent": [
      1525757739686
    ]
  },
  {
    "identifier": 1525757739692,
    "value": "Reporting",
    "type": "SubSubTrack",
    "children": [

    ],
    "parent": [
      1525757739686
    ]
  },
  {
    "identifier": 1525757739693,
    "value": "Data Management",
    "type": "SubSubTrack",
    "children": [

    ],
    "parent": [
      1525757739686
    ]
  },
  {
    "identifier": 1525757739694,
    "value": "Compliance & Controls",
    "type": "SubSubTrack",
    "children": [

    ],
    "parent": [
      1525757739686
    ]
  },
  {
    "identifier": 1525757739695,
    "value": "Wealth Management",
    "type": "SubSubTrack",
    "children": [

    ],
    "parent": [
      1525757739686
    ]
  },
  {
    "identifier": 1525757739696,
    "value": "Asset Management",
    "type": "SubSubTrack",
    "children": [

    ],
    "parent": [
      1525757739686
    ]
  },
  {
    "identifier": 1525757739697,
    "value": "Investment Banking",
    "type": "SubSubTrack",
    "children": [

    ],
    "parent": [
      1525757739686
    ]
  },
  {
    "identifier": 1525757739686,
    "value": "Capital Markets",
    "type": "SubTrack",
    "children": [
      1525757739687,
      1525757739688,
      1525757739689,
      1525757739690,
      1525757739691,
      1525757739692,
      1525757739693,
      1525757739694,
      1525757739695,
      1525757739696,
      1525757739697
    ],
    "parent": [
      1525757739681
    ]
  },
  {
    "identifier": 1525757739700,
    "value": "Risk and Compliance Industry Insights",
    "type": "SubSubTrack",
    "children": [

    ],
    "parent": [
      1525757739699
    ]
  },
  {
    "identifier": 1525757739701,
    "value": "Risk Management",
    "type": "SubSubTrack",
    "children": [

    ],
    "parent": [
      1525757739699
    ]
  },
  {
    "identifier": 1525757739702,
    "value": "Compliance Management",
    "type": "SubSubTrack",
    "children": [

    ],
    "parent": [
      1525757739699
    ]
  },
  {
    "identifier": 1525757739699,
    "value": "Risk and Compliance",
    "type": "SubTrack",
    "children": [
      1525757739700,
      1525757739701,
      1525757739702
    ],
    "parent": [
      1525757739681
    ]
  },
  {
    "identifier": 1525757739704,
    "value": "Cards and Payments Industry Insights",
    "type": "SubSubTrack",
    "children": [

    ],
    "parent": [
      1525757739703
    ]
  },
  {
    "identifier": 1525757739705,
    "value": "Card Management",
    "type": "SubSubTrack",
    "children": [

    ],
    "parent": [
      1525757739703
    ]
  },
  {
    "identifier": 1525757739706,
    "value": "Core Payments",
    "type": "SubSubTrack",
    "children": [

    ],
    "parent": [
      1525757739703
    ]
  },
  {
    "identifier": 1525757739703,
    "value": "Cards and Payments",
    "type": "SubTrack",
    "children": [
      1525757739704,
      1525757739705,
      1525757739706
    ],
    "parent": [
      1525757739681
    ]
  },
  {
    "identifier": 1525757739681,
    "value": "Financial Services",
    "type": "Track",
    "children": [
      1525757739682,
      1525757739686,
      1525757739699,
      1525757739703
    ],
    "parent": [
      1525757739680
    ]
  },
  {
    "identifier": 1525757739708,
    "value": "Healthcare Industry Insights",
    "type": "SubTrack",
    "children": [
    ],
    "parent": [
      1525757739707
    ]
  },
  {
    "identifier": 1525757739710,
    "value": "Sales Quoting and Rating",
    "type": "SubSubTrack",
    "children": [
    ],
    "parent": [
      1525757739709
    ]
  },
  {
    "identifier": 1525757739711,
    "value": "Policy and Benefit Administration",
    "type": "SubSubTrack",
    "children": [
    ],
    "parent": [
      1525757739709
    ]
  },
  {
    "identifier": 1525757739712,
    "value": "Member Enrollment and Eligibility",
    "type": "SubSubTrack",
    "children": [
    ],
    "parent": [
      1525757739709
    ]
  },
  {
    "identifier": 1525757739713,
    "value": "Billing Management",
    "type": "SubSubTrack",
    "children": [
    ],
    "parent": [
      1525757739709
    ]
  },
  {
    "identifier": 1525757739714,
    "value": "Claims Management",
    "type": "SubSubTrack",
    "children": [
    ],
    "parent": [
      1525757739709
    ]
  },
  {
    "identifier": 1525757739715,
    "value": "Provider Network",
    "type": "SubSubTrack",
    "children": [
    ],
    "parent": [
      1525757739709
    ]
  },
  {
    "identifier": 1525757739716,
    "value": "Pharmacy Benefit Management",
    "type": "SubSubTrack",
    "children": [
    ],
    "parent": [
      1525757739709
    ]
  },
  {
    "identifier": 1525757739717,
    "value": "Medical Management",
    "type": "SubSubTrack",
    "children": [
    ],
    "parent": [
      1525757739709
    ]
  },
  {
    "identifier": 1525757739718,
    "value": "Medicare",
    "type": "SubSubTrack",
    "children": [
    ],
    "parent": [
      1525757739709
    ]
  },
  {
    "identifier": 1525757739719,
    "value": "Medicaid",
    "type": "SubSubTrack",
    "children": [
    ],
    "parent": [
      1525757739709
    ]
  },
  {
    "identifier": 1525757739720,
    "value": "Healthcare Data warehouse",
    "type": "SubSubTrack",
    "children": [
    ],
    "parent": [
      1525757739709
    ]
  },
  {
    "identifier": 1525757739721,
    "value": "Healthcare Payer Regulations",
    "type": "SubSubTrack",
    "children": [
    ],
    "parent": [
      1525757739709
    ]
  },
  {
    "identifier": 1525757739709,
    "value": "Healthcare Payer",
    "type": "SubTrack",
    "children": [
      1525757739710,
      1525757739711,
      1525757739712,
      1525757739713,
      1525757739714,
      1525757739715,
      1525757739716,
      1525757739717,
      1525757739718,
      1525757739719,
      1525757739720,
      1525757739721
    ],
    "parent": [
      1525757739707
    ]
  },
  {
    "identifier": 1525757739723,
    "value": "Clinical Services",
    "type": "SubSubTrack",
    "children": [
    ],
    "parent": [
      1525757739722
    ]
  },
  {
    "identifier": 1525757739724,
    "value": "Ancillary Services",
    "type": "SubSubTrack",
    "children": [
    ],
    "parent": [
      1525757739722
    ]
  },
  {
    "identifier": 1525757739725,
    "value": "Patient Access Systems",
    "type": "SubSubTrack",
    "children": [
    ],
    "parent": [
      1525757739722
    ]
  },
  {
    "identifier": 1525757739726,
    "value": "Revenue cycle management",
    "type": "SubSubTrack",
    "children": [
    ],
    "parent": [
      1525757739722
    ]
  },
  {
    "identifier": 1525757739727,
    "value": "Healthcare Provider Regulations",
    "type": "SubSubTrack",
    "children": [
    ],
    "parent": [
      1525757739722
    ]
  },
  {
    "identifier": 1525757739722,
    "value": "Healthcare Provider",
    "type": "SubTrack",
    "children": [
      1525757739723,
      1525757739724,
      1525757739725,
      1525757739726,
      1525757739727
    ],
    "parent": [
      1525757739707
    ]
  },
  {
    "identifier": 1525757739728,
    "value": "Healthcare Frameworks and Methodologies",
    "type": "SubTrack",
    "children": [
    ],
    "parent": [
      1525757739707
    ]
  },
  {
    "identifier": 1525757739729,
    "value": "Healthcare Packages and Technologies",
    "type": "SubTrack",
    "children": [
    ],
    "parent": [
      1525757739707
    ]
  },
  {
    "identifier": 1525757739730,
    "value": "Healthcare Innovation and Trends",
    "type": "SubTrack",
    "children": [
    ],
    "parent": [
      1525757739707
    ]
  },
  {
    "identifier": 1525757739707,
    "value": "Healthcare",
    "type": "Track",
    "children": [
      1525757739708,
      1525757739709,
      1525757739722,
      1525757739728,
      1525757739729,
      1525757739730
    ],
    "parent": [
      1525757739680
    ]
  },
  {
    "identifier": 1525757739732,
    "value": "Manufacturing Industry Insights",
    "type": "SubTrack",
    "children": [
    ],
    "parent": [
      1525757739731
    ]
  },
  {
    "identifier": 1525757739733,
    "value": "Manufacturing Innovation and Trends",
    "type": "SubTrack",
    "children": [
    ],
    "parent": [
      1525757739731
    ]
  },
  {
    "identifier": 1525757739731,
    "value": "Manufacturing",
    "type": "Track",
    "children": [
      1525757739732,
      1525757739733
    ],
    "parent": [
      1525757739680
    ]
  },
  {
    "identifier": 1525757739735,
    "value": "Insurance Industry Insights",
    "type": "SubTrack",
    "children": [
    ],
    "parent": [
      1525757739734
    ]
  },
  {
    "identifier": 1525757739736,
    "value": "Insurance Innovation and Trends",
    "type": "SubTrack",
    "children": [
    ],
    "parent": [
      1525757739734
    ]
  },
  {
    "identifier": 1525757739734,
    "value": "Insurance",
    "type": "Track",
    "children": [
      1525757739735,
      1525757739736
    ],
    "parent": [
      1525757739680
    ]
  },
  {
    "identifier": 1525757739738,
    "value": "Life Sciences Industry Insights",
    "type": "SubTrack",
    "children": [

    ],
    "parent": [
      1525757739737
    ]
  },
  {
    "identifier": 1525757739739,
    "value": "Life Sciences Innovation and Trends",
    "type": "SubTrack",
    "children": [
    ],
    "parent": [
      1525757739737
    ]
  },
  {
    "identifier": 1525757739737,
    "value": "Life Sciences",
    "type": "Track",
    "children": [
      1525757739738,
      1525757739739
    ],
    "parent": [
      1525757739680
    ]
  },
  {
    "identifier": 1525757739742,
    "value": "Industry Insights",
    "type": "SubSubTrack",
    "children": [
    ],
    "parent": [
      1525757739741
    ]
  },
  {
    "identifier": 1525757739743,
    "value": "Innovation and Trends",
    "type": "SubSubTrack",
    "children": [
    ],
    "parent": [
      1525757739741
    ]
  },
  {
    "identifier": 1525757739741,
    "value": "Oil and Gas",
    "type": "SubTrack",
    "children": [
      1525757739742,
      1525757739743
    ],
    "parent": [
      1525757739740
    ]
  },
  {
    "identifier": 1525757739745,
    "value": "Geology and Exploration",
    "type": "SubSubTrack",
    "children": [
    ],
    "parent": [
      1525757739744
    ]
  },
  {
    "identifier": 1525757739746,
    "value": "Drilling and Completions",
    "type": "SubSubTrack",
    "children": [
    ],
    "parent": [
      1525757739744
    ]
  },
  {
    "identifier": 1525757739747,
    "value": "Production Operation",
    "type": "SubSubTrack",
    "children": [
    ],
    "parent": [
      1525757739744
    ]
  },
  {
    "identifier": 1525757739748,
    "value": "Hydrocarbon Accounting and Agreements",
    "type": "SubSubTrack",
    "children": [
    ],
    "parent": [
      1525757739744
    ]
  },
  {
    "identifier": 1525757739749,
    "value": "Production Optimization",
    "type": "SubSubTrack",
    "children": [
    ],
    "parent": [
      1525757739744
    ]
  },
  {
    "identifier": 1525757739744,
    "value": "Upstream",
    "type": "SubTrack",
    "children": [
      1525757739745,
      1525757739746,
      1525757739747,
      1525757739748,
      1525757739749
    ],
    "parent": [
      1525757739740
    ]
  },
  {
    "identifier": 1525757739751,
    "value": "Transportation",
    "type": "SubSubTrack",
    "children": [
    ],
    "parent": [
      1525757739750
    ]
  },
  {
    "identifier": 1525757739752,
    "value": "Storage",
    "type": "SubSubTrack",
    "children": [
    ],
    "parent": [
      1525757739750
    ]
  },
  {
    "identifier": 1525757739750,
    "value": "Midstream",
    "type": "SubTrack",
    "children": [
      1525757739751,
      1525757739752
    ],
    "parent": [
      1525757739740
    ]
  },
  {
    "identifier": 1525757739754,
    "value": "Refining",
    "type": "SubSubTrack",
    "children": [
    ],
    "parent": [
      1525757739753
    ]
  },
  {
    "identifier": 1525757739755,
    "value": "Marketing",
    "type": "SubSubTrack",
    "children": [
    ],
    "parent": [
      1525757739753
    ]
  },
  {
    "identifier": 1525757739756,
    "value": "ETRM",
    "type": "SubSubTrack",
    "children": [
    ],
    "parent": [
      1525757739753
    ]
  },
  {
    "identifier": 1525757739753,
    "value": "Downstream",
    "type": "SubTrack",
    "children": [
      1525757739754,
      1525757739755,
      1525757739756
    ],
    "parent": [
      1525757739740
    ]
  },
  {
    "identifier": 1525757739740,
    "value": "Energy",
    "type": "Track",
    "children": [
      1525757739741,
      1525757739744,
      1525757739750,
      1525757739753
    ],
    "parent": [
      1525757739680
    ]
  },
  {
    "identifier": 1525757739758,
    "value": "Communications Industry Insights",
    "type": "SubTrack",
    "children": [
    ],
    "parent": [
      1525757739757
    ]
  },
  {
    "identifier": 1525757739760,
    "value": "Fulfillment",
    "type": "SubSubTrack",
    "children": [
    ],
    "parent": [
      1525757739759
    ]
  },
  {
    "identifier": 1525757739761,
    "value": "Assurance",
    "type": "SubSubTrack",
    "children": [
    ],
    "parent": [
      1525757739759
    ]
  },
  {
    "identifier": 1525757739762,
    "value": "Billing",
    "type": "SubSubTrack",
    "children": [
    ],
    "parent": [
      1525757739759
    ]
  },
  {
    "identifier": 1525757739763,
    "value": "Product Lifecycle management",
    "type": "SubSubTrack",
    "children": [
    ],
    "parent": [
      1525757739759
    ]
  },
  {
    "identifier": 1525757739764,
    "value": "Enterprise",
    "type": "SubSubTrack",
    "children": [
    ],
    "parent": [
      1525757739759
    ]
  },
  {
    "identifier": 1525757739765,
    "value": "Strategy",
    "type": "SubSubTrack",
    "children": [
    ],
    "parent": [
      1525757739759
    ]
  },
  {
    "identifier": 1525757739766,
    "value": "Infrastructure Lifecycle Management",
    "type": "SubSubTrack",
    "children": [
    ],
    "parent": [
      1525757739759
    ]
  },
  {
    "identifier": 1525757739767,
    "value": "Across Domain Concepts",
    "type": "SubSubTrack",
    "children": [
    ],
    "parent": [
      1525757739759
    ]
  },
  {
    "identifier": 1525757739759,
    "value": "CSP Functional Domains",
    "type": "SubTrack",
    "children": [
      1525757739760,
      1525757739761,
      1525757739762,
      1525757739763,
      1525757739764,
      1525757739765,
      1525757739766,
      1525757739767
    ],
    "parent": [
      1525757739757
    ]
  },
  {
    "identifier": 1525757739768,
    "value": "Telecom OSS and BSS Concepts",
    "type": "SubTrack",
    "children": [
    ],
    "parent": [
      1525757739757
    ]
  },
  {
    "identifier": 1525757739769,
    "value": "Telecom Technologies",
    "type": "SubTrack",
    "children": [
    ],
    "parent": [
      1525757739757
    ]
  },
  {
    "identifier": 1525757739770,
    "value": "Communication Frameworks and Methodologies",
    "type": "SubTrack",
    "children": [
    ],
    "parent": [
      1525757739757
    ]
  },
  {
    "identifier": 1525757739771,
    "value": "Industry Tools Packages and Technologies",
    "type": "SubTrack",
    "children": [
    ],
    "parent": [
      1525757739757
    ]
  },
  {
    "identifier": 1525757739772,
    "value": "Communication  Business Process and Solutions",
    "type": "SubTrack",
    "children": [
    ],
    "parent": [
      1525757739757
    ]
  },
  {
    "identifier": 1525757739773,
    "value": "Communication Case Studies",
    "type": "SubTrack",
    "children": [
    ],
    "parent": [
      1525757739757
    ]
  },
  {
    "identifier": 1525757739774,
    "value": "Communication Innovation and Trends",
    "type": "SubTrack",
    "children": [
    ],
    "parent": [
      1525757739757
    ]
  },
  {
    "identifier": 1525757739757,
    "value": "Communications",
    "type": "Track",
    "children": [
      1525757739758,
      1525757739759,
      1525757739768,
      1525757739769,
      1525757739770,
      1525757739771,
      1525757739772,
      1525757739773,
      1525757739774
    ],
    "parent": [
      1525757739680
    ]
  },
  {
    "identifier": 1525757739777,
    "value": "Travel and Hospitality Industry Insights",
    "type": "SubSubTrack",
    "children": [
    ],
    "parent": [
      1525757739776
    ]
  },
  {
    "identifier": 1525757739778,
    "value": "Guest Experience",
    "type": "SubSubTrack",
    "children": [
    ],
    "parent": [
      1525757739776
    ]
  },
  {
    "identifier": 1525757739779,
    "value": "Operations",
    "type": "SubSubTrack",
    "children": [
    ],
    "parent": [
      1525757739776
    ]
  },
  {
    "identifier": 1525757739780,
    "value": "Marketing and Commercial",
    "type": "SubSubTrack",
    "children": [
    ],
    "parent": [
      1525757739776
    ]
  },
  {
    "identifier": 1525757739781,
    "value": "Corporate Management Functions",
    "type": "SubSubTrack",
    "children": [
    ],
    "parent": [
      1525757739776
    ]
  },
  {
    "identifier": 1525757739782,
    "value": "Industry Tools, Packages and Technologies",
    "type": "SubSubTrack",
    "children": [
    ],
    "parent": [
      1525757739776
    ]
  },
  {
    "identifier": 1525757739783,
    "value": "Industry Innovation and Trends",
    "type": "SubSubTrack",
    "children": [
    ],
    "parent": [
      1525757739776
    ]
  },
  {
    "identifier": 1525757739776,
    "value": "Travel and Hospitality",
    "type": "SubTrack",
    "children": [
      1525757739777,
      1525757739778,
      1525757739779,
      1525757739780,
      1525757739781,
      1525757739782,
      1525757739783
    ],
    "parent": [
      1525757739775
    ]
  },
  {
    "identifier": 1525757739785,
    "value": "Education and Training Industry Insights",
    "type": "SubSubTrack",
    "children": [
    ],
    "parent": [
      1525757739784
    ]
  },
  {
    "identifier": 1525757739787,
    "value": "K-12 Education",
    "type": "SubSubTrack",
    "children": [
    ],
    "parent": [
      1525757739784
    ]
  },
  {
    "identifier": 1525757739788,
    "value": "Higher Education",
    "type": "SubSubTrack",
    "children": [
    ],
    "parent": [
      1525757739784
    ]
  },
  {
    "identifier": 1525757739789,
    "value": "Corporate Training",
    "type": "SubSubTrack",
    "children": [
    ],
    "parent": [
      1525757739784
    ]
  },
  {
    "identifier": 1525757739790,
    "value": "Industry Packages and Technologies",
    "type": "SubSubTrack",
    "children": [
    ],
    "parent": [
      1525757739784
    ]
  },
  {
    "identifier": 1525757739791,
    "value": "Industry Innovation and Trends",
    "type": "SubSubTrack",
    "children": [
    ],
    "parent": [
      1525757739784
    ]
  },
  {
    "identifier": 1525757739784,
    "value": "Education and Training",
    "type": "SubTrack",
    "children": [
      1525757739785,
      1525757739787,
      1525757739788,
      1525757739789,
      1525757739790,
      1525757739791
    ],
    "parent": [
      1525757739775
    ]
  },
  {
    "identifier": 1525757739775,
    "value": "Services",
    "type": "Track",
    "children": [
      1525757739776,
      1525757739784
    ],
    "parent": [
      1525757739680
    ]
  },
  {
    "identifier": 1525757739793,
    "value": "Retail Industry Insights",
    "type": "SubTrack",
    "children": [
    ],
    "parent": [
      1525757739792
    ]
  },
  {
    "identifier": 1525757739794,
    "value": "Retail Innovation and Trends",
    "type": "SubTrack",
    "children": [
    ],
    "parent": [
      1525757739792
    ]
  },
  {
    "identifier": 1525757739795,
    "value": "Allocation and Replenishment",
    "type": "SubTrack",
    "children": [
    ],
    "parent": [
      1525757739792
    ]
  },
  {
    "identifier": 1525757739796,
    "value": "Allocations",
    "type": "SubTrack",
    "children": [
    ],
    "parent": [
      1525757739792
    ]
  },
  {
    "identifier": 1525757739797,
    "value": "Analytical CRM",
    "type": "SubTrack",
    "children": [
    ],
    "parent": [
      1525757739792
    ]
  },
  {
    "identifier": 1525757739798,
    "value": "Asset management",
    "type": "SubTrack",
    "children": [
    ],
    "parent": [
      1525757739792
    ]
  },
  {
    "identifier": 1525757739799,
    "value": "Category Management",
    "type": "SubTrack",
    "children": [
    ],
    "parent": [
      1525757739792
    ]
  },
  {
    "identifier": 1525757739801,
    "value": "Channel Management",
    "type": "SubTrack",
    "children": [
    ],
    "parent": [
      1525757739792
    ]
  },
  {
    "identifier": 1525757739802,
    "value": "Demand Management",
    "type": "SubTrack",
    "children": [
    ],
    "parent": [
      1525757739792
    ]
  },
  {
    "identifier": 1525757739803,
    "value": "Human Capital Management",
    "type": "SubTrack",
    "children": [
    ],
    "parent": [
      1525757739792
    ]
  },
  {
    "identifier": 1525757739804,
    "value": "Invoice matching",
    "type": "SubTrack",
    "children": [
    ],
    "parent": [
      1525757739792
    ]
  },
  {
    "identifier": 1525757739805,
    "value": "Item Planning",
    "type": "SubTrack",
    "children": [
    ],
    "parent": [
      1525757739792
    ]
  },
  {
    "identifier": 1525757739806,
    "value": "Loss Prevention",
    "type": "SubTrack",
    "children": [
    ],
    "parent": [
      1525757739792
    ]
  },
  {
    "identifier": 1525757739807,
    "value": "Market Research",
    "type": "SubTrack",
    "children": [
    ],
    "parent": [
      1525757739792
    ]
  },
  {
    "identifier": 1525757739808,
    "value": "Master Data Management",
    "type": "SubTrack",
    "children": [
    ],
    "parent": [
      1525757739792
    ]
  },
  {
    "identifier": 1525757739809,
    "value": "Merchandising system",
    "type": "SubTrack",
    "children": [
    ],
    "parent": [
      1525757739792
    ]
  },
  {
    "identifier": 1525757739810,
    "value": "Merchandize Lifecycle Management",
    "type": "SubTrack",
    "children": [
    ],
    "parent": [
      1525757739792
    ]
  },
  {
    "identifier": 1525757739811,
    "value": "Point of Sale Systems",
    "type": "SubTrack",
    "children": [
    ],
    "parent": [
      1525757739792
    ]
  },
  {
    "identifier": 1525757739812,
    "value": "Price Management",
    "type": "SubTrack",
    "children": [
    ],
    "parent": [
      1525757739792
    ]
  },
  {
    "identifier": 1525757739813,
    "value": "Retail Supply Chain & Distribution",
    "type": "SubTrack",
    "children": [
    ],
    "parent": [
      1525757739792
    ]
  },
  {
    "identifier": 1525757739814,
    "value": "Returns management",
    "type": "SubTrack",
    "children": [
    ],
    "parent": [
      1525757739792
    ]
  },
  {
    "identifier": 1525757739815,
    "value": "Sales audit",
    "type": "SubTrack",
    "children": [
    ],
    "parent": [
      1525757739792
    ]
  },
  {
    "identifier": 1525757739816,
    "value": "Shopper Experience Management",
    "type": "SubTrack",
    "children": [
    ],
    "parent": [
      1525757739792
    ]
  },
  {
    "identifier": 1525757739817,
    "value": "Space optimization",
    "type": "SubTrack",
    "children": [
    ],
    "parent": [
      1525757739792
    ]
  },
  {
    "identifier": 1525757739818,
    "value": "Trade Management",
    "type": "SubTrack",
    "children": [
    ],
    "parent": [
      1525757739792
    ]
  },
  {
    "identifier": 1525757739819,
    "value": "Vendor Managed Inventory",
    "type": "SubTrack",
    "children": [
    ],
    "parent": [
      1525757739792
    ]
  },
  {
    "identifier": 1525757739820,
    "value": "Warehouse management",
    "type": "SubTrack",
    "children": [
    ],
    "parent": [
      1525757739792
    ]
  },
  {
    "identifier": 1525757739792,
    "value": "Retail",
    "type": "Track",
    "children": [
      1525757739793,
      1525757739794,
      1525757739795,
      1525757739796,
      1525757739797,
      1525757739798,
      1525757739799,
      1525757739801,
      1525757739802,
      1525757739803,
      1525757739804,
      1525757739805,
      1525757739806,
      1525757739807,
      1525757739808,
      1525757739809,
      1525757739810,
      1525757739811,
      1525757739812,
      1525757739813,
      1525757739814,
      1525757739815,
      1525757739816,
      1525757739817,
      1525757739818,
      1525757739819,
      1525757739820
    ],
    "parent": [
      1525757739680
    ]
  },
  {
    "identifier": 1525757739822,
    "value": "CPG Industry Insights",
    "type": "SubTrack",
    "children": [
    ],
    "parent": [
      1525757739821
    ]
  },
  {
    "identifier": 1525757739823,
    "value": "CPG Industry Innovation and Trends",
    "type": "SubTrack",
    "children": [
    ],
    "parent": [
      1525757739821
    ]
  },
  {
    "identifier": 1525757739824,
    "value": "Analytics",
    "type": "SubTrack",
    "children": [
    ],
    "parent": [
      1525757739821
    ]
  },
  {
    "identifier": 1525757739825,
    "value": "Category and Brand Management",
    "type": "SubTrack",
    "children": [
    ],
    "parent": [
      1525757739821
    ]
  },
  {
    "identifier": 1525757739826,
    "value": "Data Management",
    "type": "SubTrack",
    "children": [
    ],
    "parent": [
      1525757739821
    ]
  },
  {
    "identifier": 1525757739827,
    "value": "Electronic data Interchange",
    "type": "SubTrack",
    "children": [
    ],
    "parent": [
      1525757739821
    ]
  },
  {
    "identifier": 1525757739828,
    "value": "Financial Planning",
    "type": "SubTrack",
    "children": [
    ],
    "parent": [
      1525757739821
    ]
  },
  {
    "identifier": 1525757739829,
    "value": "Inventory",
    "type": "SubTrack",
    "children": [
    ],
    "parent": [
      1525757739821
    ]
  },
  {
    "identifier": 1525757739830,
    "value": "Key Account Management Trade Planning, Promotions",
    "type": "SubTrack",
    "children": [
    ],
    "parent": [
      1525757739821
    ]
  },
  {
    "identifier": 1525757739831,
    "value": "Manufacturing",
    "type": "SubTrack",
    "children": [
    ],
    "parent": [
      1525757739821
    ]
  },
  {
    "identifier": 1525757739832,
    "value": "Marketing Plan",
    "type": "SubTrack",
    "children": [
    ],
    "parent": [
      1525757739821
    ]
  },
  {
    "identifier": 1525757739833,
    "value": "Material Management",
    "type": "SubTrack",
    "children": [
    ],
    "parent": [
      1525757739821
    ]
  },
  {
    "identifier": 1525757739834,
    "value": "Mobility",
    "type": "SubTrack",
    "children": [
    ],
    "parent": [
      1525757739821
    ]
  },
  {
    "identifier": 1525757739835,
    "value": "New Product Development",
    "type": "SubTrack",
    "children": [
    ],
    "parent": [
      1525757739821
    ]
  },
  {
    "identifier": 1525757739836,
    "value": "Product Planning and Demand forecasting",
    "type": "SubTrack",
    "children": [
    ],
    "parent": [
      1525757739821
    ]
  },
  {
    "identifier": 1525757739837,
    "value": "Reporting Services",
    "type": "SubTrack",
    "children": [
    ],
    "parent": [
      1525757739821
    ]
  },
  {
    "identifier": 1525757739838,
    "value": "Research and Development",
    "type": "SubTrack",
    "children": [
    ],
    "parent": [
      1525757739821
    ]
  },
  {
    "identifier": 1525757739839,
    "value": "Route Optimization and Fleet Management",
    "type": "SubTrack",
    "children": [
    ],
    "parent": [
      1525757739821
    ]
  },
  {
    "identifier": 1525757739840,
    "value": "Sales and Operations Planning",
    "type": "SubTrack",
    "children": [
    ],
    "parent": [
      1525757739821
    ]
  },
  {
    "identifier": 1525757739841,
    "value": "Shipping",
    "type": "SubTrack",
    "children": [
    ],
    "parent": [
      1525757739821
    ]
  },
  {
    "identifier": 1525757739842,
    "value": "Supply Network and Distribution",
    "type": "SubTrack",
    "children": [
    ],
    "parent": [
      1525757739821
    ]
  },
  {
    "identifier": 1525757739843,
    "value": "Warehouse Planning and Distribution Management System",
    "type": "SubTrack",
    "children": [
    ],
    "parent": [
      1525757739821
    ]
  },
  {
    "identifier": 1525757739821,
    "value": "Consumer Packaged Goods",
    "type": "Track",
    "children": [
      1525757739822,
      1525757739823,
      1525757739824,
      1525757739825,
      1525757739826,
      1525757739827,
      1525757739828,
      1525757739829,
      1525757739830,
      1525757739831,
      1525757739832,
      1525757739833,
      1525757739834,
      1525757739835,
      1525757739836,
      1525757739837,
      1525757739838,
      1525757739839,
      1525757739840,
      1525757739841,
      1525757739842,
      1525757739843
    ],
    "parent": [
      1525757739680
    ]
  },
  {
    "identifier": 1525757739845,
    "value": "Industry Insights",
    "type": "SubTrack",
    "children": [
    ],
    "parent": [
      1525757739844
    ]
  },
  {
    "identifier": 1525757739846,
    "value": "Industry Innovation and Trends",
    "type": "SubTrack",
    "children": [
    ],
    "parent": [
      1525757739844
    ]
  },
  {
    "identifier": 1525757739847,
    "value": "Allocation management",
    "type": "SubTrack",
    "children": [
    ],
    "parent": [
      1525757739844
    ]
  },
  {
    "identifier": 1525757739848,
    "value": "Asset Management",
    "type": "SubTrack",
    "children": [
    ],
    "parent": [
      1525757739844
    ]
  },
  {
    "identifier": 1525757739850,
    "value": "Bulk carriers",
    "type": "SubTrack",
    "children": [
    ],
    "parent": [
      1525757739844
    ]
  },
  {
    "identifier": 1525757739851,
    "value": "Cargo Order Management",
    "type": "SubTrack",
    "children": [
    ],
    "parent": [
      1525757739844
    ]
  },
  {
    "identifier": 1525757739852,
    "value": "Consolidation and Brokerage",
    "type": "SubTrack",
    "children": [
    ],
    "parent": [
      1525757739844
    ]
  },
  {
    "identifier": 1525757739853,
    "value": "Demand planning and Optimization",
    "type": "SubTrack",
    "children": [
    ],
    "parent": [
      1525757739844
    ]
  },
  {
    "identifier": 1525757739854,
    "value": "Empty Repositioning",
    "type": "SubTrack",
    "children": [
    ],
    "parent": [
      1525757739844
    ]
  },
  {
    "identifier": 1525757739855,
    "value": "Equipment tracking and Management",
    "type": "SubTrack",
    "children": [
    ],
    "parent": [
      1525757739844
    ]
  },
  {
    "identifier": 1525757739856,
    "value": "Fleet Management",
    "type": "SubTrack",
    "children": [
    ],
    "parent": [
      1525757739844
    ]
  },
  {
    "identifier": 1525757739857,
    "value": "Freight & Logistics Services",
    "type": "SubTrack",
    "children": [
    ],
    "parent": [
      1525757739844
    ]
  },
  {
    "identifier": 1525757739858,
    "value": "Food Services Distribution",
    "type": "SubTrack",
    "children": [
    ],
    "parent": [
      1525757739844
    ]
  },
  {
    "identifier": 1525757739859,
    "value": "Land transportation",
    "type": "SubTrack",
    "children": [
    ],
    "parent": [
      1525757739844
    ]
  },
  {
    "identifier": 1525757739860,
    "value": "Last Mile",
    "type": "SubTrack",
    "children": [
    ],
    "parent": [
      1525757739844
    ]
  },
  {
    "identifier": 1525757739861,
    "value": "Network planning",
    "type": "SubTrack",
    "children": [
    ],
    "parent": [
      1525757739844
    ]
  },
  {
    "identifier": 1525757739862,
    "value": "Pricing and Finance",
    "type": "SubTrack",
    "children": [
    ],
    "parent": [
      1525757739844
    ]
  },
  {
    "identifier": 1525757739863,
    "value": "Regulatory",
    "type": "SubTrack",
    "children": [
    ],
    "parent": [
      1525757739844
    ]
  },
  {
    "identifier": 1525757739864,
    "value": "Route and cost management",
    "type": "SubTrack",
    "children": [
    ],
    "parent": [
      1525757739844
    ]
  },
  {
    "identifier": 1525757739865,
    "value": "Terminals",
    "type": "SubTrack",
    "children": [
    ],
    "parent": [
      1525757739844
    ]
  },
  {
    "identifier": 1525757739866,
    "value": "Transportation",
    "type": "SubTrack",
    "children": [
    ],
    "parent": [
      1525757739844
    ]
  },
  {
    "identifier": 1525757739867,
    "value": "Vendor Management",
    "type": "SubTrack",
    "children": [
    ],
    "parent": [
      1525757739844
    ]
  },
  {
    "identifier": 1525757739868,
    "value": "Warehouse management",
    "type": "SubTrack",
    "children": [
    ],
    "parent": [
      1525757739844
    ]
  },
  {
    "identifier": 1525757739844,
    "value": "Logistics and Transportation",
    "type": "Track",
    "children": [
      1525757739845,
      1525757739846,
      1525757739847,
      1525757739848,
      1525757739850,
      1525757739851,
      1525757739852,
      1525757739853,
      1525757739854,
      1525757739855,
      1525757739856,
      1525757739857,
      1525757739858,
      1525757739859,
      1525757739860,
      1525757739861,
      1525757739862,
      1525757739863,
      1525757739864,
      1525757739865,
      1525757739866,
      1525757739867,
      1525757739868
    ],
    "parent": [
      1525757739680
    ]
  },
  {
    "identifier": 1525757739680,
    "value": "Domain",
    "type": "Category",
    "children": [
      1525757739681,
      1525757739707,
      1525757739731,
      1525757739734,
      1525757739737,
      1525757739740,
      1525757739757,
      1525757739775,
      1525757739792,
      1525757739821,
      1525757739844
    ],
    "parent": [
      1525338740921
    ]
  },
  {
    "identifier": 1525338740988,
    "value": "Dev Competencies",
    "type": "Track",
    "children": [

    ],
    "parent": [
      1525338740987
    ]
  },
  {
    "identifier": 1525338740989,
    "value": "PM competencies",
    "type": "Track",
    "children": [

    ],
    "parent": [
      1525338740987
    ]
  },
  {
    "identifier": 1525338740990,
    "value": "Design Thinking",
    "type": "Track",
    "children": [

    ],
    "parent": [
      1525338740987
    ]
  },
  {
    "identifier": 1525338740991,
    "value": "High Impact Communication",
    "type": "Track",
    "children": [

    ],
    "parent": [
      1525338740987
    ]
  },
  {
    "identifier": 1525338740992,
    "value": "Planning and Organizing",
    "type": "Track",
    "children": [

    ],
    "parent": [
      1525338740987
    ]
  },
  {
    "identifier": 1525338740993,
    "value": "Building Strategic Perspective",
    "type": "Track",
    "children": [

    ],
    "parent": [
      1525338740987
    ]
  },
  {
    "identifier": 1525338740994,
    "value": "Building Teams",
    "type": "Track",
    "children": [

    ],
    "parent": [
      1525338740987
    ]
  },
  {
    "identifier": 1525338740995,
    "value": "Building Collaborative Partnership",
    "type": "Track",
    "children": [

    ],
    "parent": [
      1525338740987
    ]
  },
  {
    "identifier": 1525338740996,
    "value": "Change Management",
    "type": "Track",
    "children": [

    ],
    "parent": [
      1525338740987
    ]
  },
  {
    "identifier": 1525338740997,
    "value": "Driving Organizational Results",
    "type": "Track",
    "children": [

    ],
    "parent": [
      1525338740987
    ]
  },
  {
    "identifier": 1525338740998,
    "value": "Learning and Innovation",
    "type": "Track",
    "children": [

    ],
    "parent": [
      1525338740987
    ]
  },
  {
    "identifier": 1525338740999,
    "value": "Business Acumen",
    "type": "Track",
    "children": [
    ],
    "parent": [
      1525338740987
    ]
  },
  {
    "identifier": 1525780232370,
    "value": "Analytical Ability",
    "type": "Track",
    "children": [
    ],
    "parent": [
      1525338740987
    ]
  },
  {
    "identifier": 1525780232371,
    "value": "Customer Orientation",
    "type": "Track",
    "children": [

    ],
    "parent": [
      1525338740987
    ]
  },
  {
    "identifier": 1525338740987,
    "value": "Behavioral and Business Skills",
    "type": "Category",
    "children": [
      1525338740988,
      1525338740989,
      1525338740990,
      1525338740991,
      1525338740992,
      1525338740993,
      1525338740994,
      1525338740995,
      1525338740996,
      1525338740997,
      1525338740998,
      1525338740999
    ],
    "parent": [
      1525338740921
    ]
  },
  {
    "identifier": 1525338741002,
    "value": "Corporate",
    "type": "SubTrack",
    "children": [

    ],
    "parent": [
      1525338741001
    ]
  },
  {
    "identifier": 1525338741003,
    "value": "Employer",
    "type": "SubTrack",
    "children": [

    ],
    "parent": [
      1525338741001
    ]
  },
  {
    "identifier": 1525338741001,
    "value": "Brand",
    "type": "Track",
    "children": [
      1525338741002,
      1525338741003
    ],
    "parent": [
      1525338741000
    ]
  },
  {
    "identifier": 1525338741006,
    "value": "Mainframe Modernization as Offering",
    "type": "SubSubTrack",
    "children": [

    ],
    "parent": [
      1525338741005
    ]
  },
  {
    "identifier": 1525338741007,
    "value": "Agile and DevOps as Offering",
    "type": "SubSubTrack",
    "children": [

    ],
    "parent": [
      1525338741005
    ]
  },
  {
    "identifier": 1525338741008,
    "value": "Open Source Development as Offering",
    "type": "SubSubTrack",
    "children": [

    ],
    "parent": [
      1525338741005
    ]
  },
  {
    "identifier": 1525338741005,
    "value": "ADM as Theme",
    "type": "SubTrack",
    "children": [
      1525338741006,
      1525338741007,
      1525338741008
    ],
    "parent": [
      1525338741004
    ]
  },
  {
    "identifier": 1525338741010,
    "value": "AI and Automation as Offering",
    "type": "SubSubTrack",
    "children": [

    ],
    "parent": [
      1525338741009
    ]
  },
  {
    "identifier": 1525338741009,
    "value": "AI and AUTOMATION as Theme",
    "type": "SubTrack",
    "children": [
      1525338741010
    ],
    "parent": [
      1525338741004
    ]
  },
  {
    "identifier": 1525338741012,
    "value": "Analytics as Offering",
    "type": "SubSubTrack",
    "children": [

    ],
    "parent": [
      1525338741011
    ]
  },
  {
    "identifier": 1525338741011,
    "value": "ANALYTICS as Theme",
    "type": "SubTrack",
    "children": [
      1525338741012
    ],
    "parent": [
      1525338741004
    ]
  },
  {
    "identifier": 1525338741014,
    "value": "API Economy as Offering",
    "type": "SubSubTrack",
    "children": [

    ],
    "parent": [
      1525338741013
    ]
  },
  {
    "identifier": 1525338741015,
    "value": "Digital Process Automation as Offering",
    "type": "SubSubTrack",
    "children": [

    ],
    "parent": [
      1525338741013
    ]
  },
  {
    "identifier": 1525338741013,
    "value": "API and DPA as Theme",
    "type": "SubTrack",
    "children": [
      1525338741014,
      1525338741015
    ],
    "parent": [
      1525338741004
    ]
  },
  {
    "identifier": 1525338741017,
    "value": "Blockchain as Offering",
    "type": "SubSubTrack",
    "children": [

    ],
    "parent": [
      1525338741016
    ]
  },
  {
    "identifier": 1525338741016,
    "value": "BLOCKCHAIN as Theme",
    "type": "SubTrack",
    "children": [
      1525338741017
    ],
    "parent": [
      1525338741004
    ]
  },
  {
    "identifier": 1525338741019,
    "value": "Enterprise Cloud Ecosystem as Offering",
    "type": "SubSubTrack",
    "children": [

    ],
    "parent": [
      1525338741018
    ]
  },
  {
    "identifier": 1525338741020,
    "value": "Service Now / ESM Caf as Offering",
    "type": "SubSubTrack",
    "children": [

    ],
    "parent": [
      1525338741018
    ]
  },
  {
    "identifier": 1525338741018,
    "value": "CLOUD and INFRA as Theme",
    "type": "SubTrack",
    "children": [
      1525338741019,
      1525338741020
    ],
    "parent": [
      1525338741004
    ]
  },
  {
    "identifier": 1525338741022,
    "value": "Cyber Security as Offering",
    "type": "SubSubTrack",
    "children": [

    ],
    "parent": [
      1525338741021
    ]
  },
  {
    "identifier": 1525338741021,
    "value": "CYBER SECURITY as Theme",
    "type": "SubTrack",
    "children": [
      1525338741022
    ],
    "parent": [
      1525338741004
    ]
  },
  {
    "identifier": 1525338741024,
    "value": "Digital Experience as Offering",
    "type": "SubSubTrack",
    "children": [

    ],
    "parent": [
      1525338741023
    ]
  },
  {
    "identifier": 1525338741023,
    "value": "DIGITAL EXPERIENCE as Theme",
    "type": "SubTrack",
    "children": [
      1525338741024
    ],
    "parent": [
      1525338741004
    ]
  },
  {
    "identifier": 1525338741026,
    "value": "Engineering Services as Offering",
    "type": "SubSubTrack",
    "children": [

    ],
    "parent": [
      1525338741025
    ]
  },
  {
    "identifier": 1525338741027,
    "value": "Internet of Things(IoT) as Offering",
    "type": "SubSubTrack",
    "children": [

    ],
    "parent": [
      1525338741025
    ]
  },
  {
    "identifier": 1525338741025,
    "value": "Engineering as Theme",
    "type": "SubTrack",
    "children": [
      1525338741026,
      1525338741027
    ],
    "parent": [
      1525338741004
    ]
  },
  {
    "identifier": 1525338741029,
    "value": "Big Data Testing as Offering",
    "type": "SubSubTrack",
    "children": [

    ],
    "parent": [
      1525338741028
    ]
  },
  {
    "identifier": 1525338741030,
    "value": "Mobile Testing as Offering",
    "type": "SubSubTrack",
    "children": [

    ],
    "parent": [
      1525338741028
    ]
  },
  {
    "identifier": 1525338741028,
    "value": "Specialized Validation Services as Theme",
    "type": "SubTrack",
    "children": [
      1525338741029,
      1525338741030
    ],
    "parent": [
      1525338741004
    ]
  },
  {
    "identifier": 1525338741032,
    "value": "MS Dynamics as Offering",
    "type": "SubSubTrack",
    "children": [

    ],
    "parent": [
      1525338741031
    ]
  },
  {
    "identifier": 1525338741031,
    "value": "Strategic Cloud Apps - MS Dynamics as Theme",
    "type": "SubTrack",
    "children": [
      1525338741032
    ],
    "parent": [
      1525338741004
    ]
  },
  {
    "identifier": 1525338741035,
    "value": "Oracle Cloud as Offering",
    "type": "SubSubTrack",
    "children": [

    ],
    "parent": [
      1525338741034
    ]
  },
  {
    "identifier": 1525338741034,
    "value": "Strategic Cloud Apps - Oracle as Theme",
    "type": "SubTrack",
    "children": [
      1525338741035
    ],
    "parent": [
      1525338741004
    ]
  },
  {
    "identifier": 1525338741037,
    "value": "Salesforce.com as Offering",
    "type": "SubSubTrack",
    "children": [

    ],
    "parent": [
      1525338741036
    ]
  },
  {
    "identifier": 1525338741036,
    "value": "Strategic Cloud Apps - SFDC as Theme",
    "type": "SubTrack",
    "children": [
      1525338741037
    ],
    "parent": [
      1525338741004
    ]
  },
  {
    "identifier": 1525338741039,
    "value": "SAP Fiori as Offering",
    "type": "SubSubTrack",
    "children": [

    ],
    "parent": [
      1525338741038
    ]
  },
  {
    "identifier": 1525338741040,
    "value": "SAP S/4 HANA as Offering",
    "type": "SubSubTrack",
    "children": [
    ],
    "parent": [
      1525338741038
    ]
  },
  {
    "identifier": 1525338741041,
    "value": "SAP Success Factors as Offering",
    "type": "SubSubTrack",
    "children": [
    ],
    "parent": [
      1525338741038
    ]
  },
  {
    "identifier": 1525338741038,
    "value": "Strategic Cloud Apps - SAP as Theme",
    "type": "SubTrack",
    "children": [
      1525338741039,
      1525338741040,
      1525338741041
    ],
    "parent": [
      1525338741004
    ]
  },
  {
    "identifier": 1525338741043,
    "value": "Workplace Transformation as Offering",
    "type": "SubSubTrack",
    "children": [

    ],
    "parent": [
      1525338741042
    ]
  },
  {
    "identifier": 1525338741042,
    "value": "Workplace Transformation as Theme",
    "type": "SubTrack",
    "children": [
      1525338741043
    ],
    "parent": [
      1525338741004
    ]
  },
  {
    "identifier": 1525338741004,
    "value": "Services",
    "type": "Track",
    "children": [
      1525338741005,
      1525338741009,
      1525338741011,
      1525338741013,
      1525338741016,
      1525338741018,
      1525338741021,
      1525338741023,
      1525338741025,
      1525338741028,
      1525338741031,
      1525338741034,
      1525338741036,
      1525338741038,
      1525338741042
    ],
    "parent": [
      1525338741000
    ]
  },
  {
    "identifier": 1525338741046,
    "value": "Consumer Banking as Offering",
    "type": "SubSubTrack",
    "children": [

    ],
    "parent": [
      1525338741045
    ]
  },
  {
    "identifier": 1525338741047,
    "value": "Commercial Banking as Offering",
    "type": "SubSubTrack",
    "children": [

    ],
    "parent": [
      1525338741045
    ]
  },
  {
    "identifier": 1525338741048,
    "value": "Capital Markets as Offering",
    "type": "SubSubTrack",
    "children": [

    ],
    "parent": [
      1525338741045
    ]
  },
  {
    "identifier": 1525338741049,
    "value": "Cards and Payments as Offering",
    "type": "SubSubTrack",
    "children": [

    ],
    "parent": [
      1525338741045
    ]
  },
  {
    "identifier": 1525338741050,
    "value": "Risk and Compliance as Offering",
    "type": "SubSubTrack",
    "children": [

    ],
    "parent": [
      1525338741045
    ]
  },
  {
    "identifier": 1525338741045,
    "value": "Financial Services as Theme",
    "type": "SubTrack",
    "children": [
      1525338741046,
      1525338741047,
      1525338741048,
      1525338741049,
      1525338741050
    ],
    "parent": [
      1525338741044
    ]
  },
  {
    "identifier": 1525338741053,
    "value": "Insurance  as Offering",
    "type": "SubSubTrack",
    "children": [

    ],
    "parent": [
      1525338741052
    ]
  },
  {
    "identifier": 1525338741052,
    "value": "Insurance  as Theme",
    "type": "SubTrack",
    "children": [
      1525338741053
    ],
    "parent": [
      1525338741044
    ]
  },
  {
    "identifier": 1525338741055,
    "value": "Retail as Offering",
    "type": "SubSubTrack",
    "children": [

    ],
    "parent": [
      1525338741054
    ]
  },
  {
    "identifier": 1525338741054,
    "value": "Retail as Theme",
    "type": "SubTrack",
    "children": [
      1525338741055
    ],
    "parent": [
      1525338741044
    ]
  },
  {
    "identifier": 1525338741057,
    "value": "Consumer Packaged Goods as Offering",
    "type": "SubSubTrack",
    "children": [

    ],
    "parent": [
      1525338741056
    ]
  },
  {
    "identifier": 1525338741056,
    "value": "Consumer Packaged Goods as Theme",
    "type": "SubTrack",
    "children": [
      1525338741057
    ],
    "parent": [
      1525338741044
    ]
  },
  {
    "identifier": 1525338741059,
    "value": "Automotive as Offering",
    "type": "SubSubTrack",
    "children": [

    ],
    "parent": [
      1525338741058
    ]
  },
  {
    "identifier": 1525338741060,
    "value": "Aerospace and Defense as Offering",
    "type": "SubSubTrack",
    "children": [

    ],
    "parent": [
      1525338741058
    ]
  },
  {
    "identifier": 1525338741061,
    "value": "Industrial Manufacturing as Offering",
    "type": "SubSubTrack",
    "children": [

    ],
    "parent": [
      1525338741058
    ]
  },
  {
    "identifier": 1525338741058,
    "value": "Manufacturing  as Theme",
    "type": "SubTrack",
    "children": [
      1525338741059,
      1525338741060,
      1525338741061
    ],
    "parent": [
      1525338741044
    ]
  },
  {
    "identifier": 1525338741063,
    "value": "Hi-Tech as Offering",
    "type": "SubSubTrack",
    "children": [

    ],
    "parent": [
      1525338741062
    ]
  },
  {
    "identifier": 1525338741062,
    "value": "Hi-Tech as Theme",
    "type": "SubTrack",
    "children": [
      1525338741063
    ],
    "parent": [
      1525338741044
    ]
  },
  {
    "identifier": 1525338741065,
    "value": "Communications, Media and Entertainment as Offering",
    "type": "SubSubTrack",
    "children": [

    ],
    "parent": [
      1525338741064
    ]
  },
  {
    "identifier": 1525338741064,
    "value": "Communications, Media and Entertainment as Theme",
    "type": "SubTrack",
    "children": [
      1525338741065
    ],
    "parent": [
      1525338741044
    ]
  },
  {
    "identifier": 1525338741067,
    "value": "Oil and Gas as Offering",
    "type": "SubSubTrack",
    "children": [

    ],
    "parent": [
      1525338741066
    ]
  },
  {
    "identifier": 1525338741066,
    "value": "Oil and Gas as Theme",
    "type": "SubTrack",
    "children": [
      1525338741067
    ],
    "parent": [
      1525338741044
    ]
  },
  {
    "identifier": 1525338741069,
    "value": "Life Sciences and Healthcare as Offering",
    "type": "SubSubTrack",
    "children": [

    ],
    "parent": [
      1525338741068
    ]
  },
  {
    "identifier": 1525338741068,
    "value": "Life Sciences and Healthcare as Theme",
    "type": "SubTrack",
    "children": [
      1525338741069
    ],
    "parent": [
      1525338741044
    ]
  },
  {
    "identifier": 1525338741071,
    "value": "Metals and Mining as Offering",
    "type": "SubSubTrack",
    "children": [

    ],
    "parent": [
      1525338741070
    ]
  },
  {
    "identifier": 1525338741072,
    "value": "Agribusiness as Offering",
    "type": "SubSubTrack",
    "children": [

    ],
    "parent": [
      1525338741070
    ]
  },
  {
    "identifier": 1525338741073,
    "value": "Chemicals as Offering",
    "type": "SubSubTrack",
    "children": [

    ],
    "parent": [
      1525338741070
    ]
  },
  {
    "identifier": 1525338741070,
    "value": "Resources  as Theme",
    "type": "SubTrack",
    "children": [
      1525338741071,
      1525338741072,
      1525338741073
    ],
    "parent": [
      1525338741044
    ]
  },
  {
    "identifier": 1525338741075,
    "value": "Utilities  as Offering",
    "type": "SubSubTrack",
    "children": [

    ],
    "parent": [
      1525338741074
    ]
  },
  {
    "identifier": 1525338741074,
    "value": "Utilities  as Theme",
    "type": "SubTrack",
    "children": [
      1525338741075
    ],
    "parent": [
      1525338741044
    ]
  },
  {
    "identifier": 1525338741077,
    "value": "Logistics as Offering",
    "type": "SubSubTrack",
    "children": [

    ],
    "parent": [
      1525338741076
    ]
  },
  {
    "identifier": 1525338741076,
    "value": "Logistics as Theme",
    "type": "SubTrack",
    "children": [
      1525338741077
    ],
    "parent": [
      1525338741044
    ]
  },
  {
    "identifier": 1525338741079,
    "value": "Information Services and Publishing as Offering",
    "type": "SubSubTrack",
    "children": [

    ],
    "parent": [
      1525338741078
    ]
  },
  {
    "identifier": 1525338741078,
    "value": "Information Services and Publishing as Theme",
    "type": "SubTrack",
    "children": [
      1525338741079
    ],
    "parent": [
      1525338741044
    ]
  },
  {
    "identifier": 1525338741081,
    "value": "Public Service  as Offering",
    "type": "SubSubTrack",
    "children": [

    ],
    "parent": [
      1525338741080
    ]
  },
  {
    "identifier": 1525338741080,
    "value": "Public Service  as Theme",
    "type": "SubTrack",
    "children": [
      1525338741081
    ],
    "parent": [
      1525338741044
    ]
  },
  {
    "identifier": 1525338741044,
    "value": "Industries",
    "type": "Track",
    "children": [
      1525338741045,
      1525338741052,
      1525338741054,
      1525338741056,
      1525338741058,
      1525338741062,
      1525338741064,
      1525338741066,
      1525338741068,
      1525338741070,
      1525338741074,
      1525338741076,
      1525338741078,
      1525338741080
    ],
    "parent": [
      1525338741000
    ]
  },
  {
    "identifier": 1525338741084,
    "value": " Integrated Device Monitoring",
    "type": "SubSubTrack",
    "children": [

    ],
    "parent": [
      1525338741083
    ]
  },
  {
    "identifier": 1525338741085,
    "value": " Real-time Expertise Manager",
    "type": "SubSubTrack",
    "children": [

    ],
    "parent": [
      1525338741083
    ]
  },
  {
    "identifier": 1525338741086,
    "value": " Robotic Process Automation",
    "type": "SubSubTrack",
    "children": [

    ],
    "parent": [
      1525338741083
    ]
  },
  {
    "identifier": 1525338741087,
    "value": " Smart User Environment",
    "type": "SubSubTrack",
    "children": [

    ],
    "parent": [
      1525338741083
    ]
  },
  {
    "identifier": 1525338741088,
    "value": "Infosys Nia Platform",
    "type": "SubSubTrack",
    "children": [

    ],
    "parent": [
      1525338741083
    ]
  },
  {
    "identifier": 1525338741089,
    "value": "Nia Guided Buying",
    "type": "SubSubTrack",
    "children": [

    ],
    "parent": [
      1525338741083
    ]
  },
  {
    "identifier": 1525338741090,
    "value": "Nia Procurement Assistant",
    "type": "SubSubTrack",
    "children": [

    ],
    "parent": [
      1525338741083
    ]
  },
  {
    "identifier": 1525338741091,
    "value": "Nia Procurement Insights",
    "type": "SubSubTrack",
    "children": [

    ],
    "parent": [
      1525338741083
    ]
  },
  {
    "identifier": 1525338741092,
    "value": "Nia Tail Spend Management",
    "type": "SubSubTrack",
    "children": [

    ],
    "parent": [
      1525338741083
    ]
  },
  {
    "identifier": 1525338741083,
    "value": "",
    "type": "SubTrack",
    "children": [
      1525338741084,
      1525338741085,
      1525338741086,
      1525338741087,
      1525338741088,
      1525338741089,
      1525338741090,
      1525338741091,
      1525338741092
    ],
    "parent": [
      1525338741082
    ]
  },
  {
    "identifier": 1525338742115,
    "value": "Finacle Overview",
    "type": "SubSubTrack",
    "children": [
    ],
    "parent": [
      1525338741093
    ]
  },
  {
    "identifier": 1525338741094,
    "value": "Finacle Core Banking",
    "type": "SubSubTrack",
    "children": [

    ],
    "parent": [
      1525338741093
    ]
  },
  {
    "identifier": 1525338741095,
    "value": "Finacle Omnichannel Hub",
    "type": "SubSubTrack",
    "children": [

    ],
    "parent": [
      1525338741093
    ]
  },
  {
    "identifier": 1525338741096,
    "value": "Finacle Online Banking",
    "type": "SubSubTrack",
    "children": [

    ],
    "parent": [
      1525338741093
    ]
  },
  {
    "identifier": 1525338741097,
    "value": "Finacle Mobile Banking",
    "type": "SubSubTrack",
    "children": [

    ],
    "parent": [
      1525338741093
    ]
  },
  {
    "identifier": 1525338741098,
    "value": "Finacle Treasury",
    "type": "SubSubTrack",
    "children": [

    ],
    "parent": [
      1525338741093
    ]
  },
  {
    "identifier": 1525338741099,
    "value": "Finacle Wealth Management",
    "type": "SubSubTrack",
    "children": [

    ],
    "parent": [
      1525338741093
    ]
  },
  {
    "identifier": 1525338741100,
    "value": "Finacle Blockchain Offerings",
    "type": "SubSubTrack",
    "children": [

    ],
    "parent": [
      1525338741093
    ]
  },
  {
    "identifier": 1525338741101,
    "value": "Finacle Payments",
    "type": "SubSubTrack",
    "children": [

    ],
    "parent": [
      1525338741093
    ]
  },
  {
    "identifier": 1525338741102,
    "value": "Finacle Origination",
    "type": "SubSubTrack",
    "children": [

    ],
    "parent": [
      1525338741093
    ]
  },
  {
    "identifier": 1525338741103,
    "value": "Finacle Liquidity Management",
    "type": "SubSubTrack",
    "children": [

    ],
    "parent": [
      1525338741093
    ]
  },
  {
    "identifier": 1525338741104,
    "value": "Finacle Youth Banking",
    "type": "SubSubTrack",
    "children": [

    ],
    "parent": [
      1525338741093
    ]
  },
  {
    "identifier": 1525338741105,
    "value": "Finacle SME Enable",
    "type": "SubSubTrack",
    "children": [

    ],
    "parent": [
      1525338741093
    ]
  },
  {
    "identifier": 1525338741106,
    "value": "Finacle Analytics",
    "type": "SubSubTrack",
    "children": [

    ],
    "parent": [
      1525338741093
    ]
  },
  {
    "identifier": 1525338741107,
    "value": "Finacle Assure",
    "type": "SubSubTrack",
    "children": [

    ],
    "parent": [
      1525338741093
    ]
  },
  {
    "identifier": 1525338741108,
    "value": "Finacle Customer Assist",
    "type": "SubSubTrack",
    "children": [

    ],
    "parent": [
      1525338741093
    ]
  },
  {
    "identifier": 1525338741109,
    "value": "Finacle CRM Solution",
    "type": "SubSubTrack",
    "children": [

    ],
    "parent": [
      1525338741093
    ]
  },
  {
    "identifier": 1525338741110,
    "value": "Finacle Direct Banking",
    "type": "SubSubTrack",
    "children": [

    ],
    "parent": [
      1525338741093
    ]
  },
  {
    "identifier": 1525338741111,
    "value": "Finacle Digital Wallet",
    "type": "SubSubTrack",
    "children": [

    ],
    "parent": [
      1525338741093
    ]
  },
  {
    "identifier": 1525338741112,
    "value": "Finacle Islamic Banking",
    "type": "SubSubTrack",
    "children": [

    ],
    "parent": [
      1525338741093
    ]
  },
  {
    "identifier": 1525338741113,
    "value": "Finanz Tools",
    "type": "SubSubTrack",
    "children": [

    ],
    "parent": [
      1525338741093
    ]
  },
  {
    "identifier": 1525338741114,
    "value": "Finacle Alerts",
    "type": "SubSubTrack",
    "children": [

    ],
    "parent": [
      1525338741093
    ]
  },
  {
    "identifier": 1525338741115,
    "value": "Finacle Mobile Teller",
    "type": "SubSubTrack",
    "children": [

    ],
    "parent": [
      1525338741093
    ]
  },
  {
    "identifier": 1525338741093,
    "value": "Finacle",
    "type": "SubTrack",
    "children": [
      1525338742115,
      1525338741094,
      1525338741095,
      1525338741096,
      1525338741097,
      1525338741098,
      1525338741099,
      1525338741100,
      1525338741101,
      1525338741102,
      1525338741103,
      1525338741104,
      1525338741105,
      1525338741106,
      1525338741107,
      1525338741108,
      1525338741109,
      1525338741110,
      1525338741111,
      1525338741112,
      1525338741113,
      1525338741114,
      1525338741115
    ],
    "parent": [
      1525338741082
    ]
  },
  {
    "identifier": 1525338741117,
    "value": "BPM Analytics",
    "type": "SubSubTrack",
    "children": [

    ],
    "parent": [
      1525338741116
    ]
  },
  {
    "identifier": 1525338741118,
    "value": "Business Transformation Services",
    "type": "SubSubTrack",
    "children": [

    ],
    "parent": [
      1525338741116
    ]
  },
  {
    "identifier": 1525338741119,
    "value": "Customer Service",
    "type": "SubSubTrack",
    "children": [

    ],
    "parent": [
      1525338741116
    ]
  },
  {
    "identifier": 1525338741120,
    "value": "Digital Business Service",
    "type": "SubSubTrack",
    "children": [

    ],
    "parent": [
      1525338741116
    ]
  },
  {
    "identifier": 1525338741121,
    "value": "Finance and Accounting",
    "type": "SubSubTrack",
    "children": [

    ],
    "parent": [
      1525338741116
    ]
  },
  {
    "identifier": 1525338741122,
    "value": "Human Resources Outsourcing",
    "type": "SubSubTrack",
    "children": [

    ],
    "parent": [
      1525338741116
    ]
  },
  {
    "identifier": 1525338741123,
    "value": "Legal Process Outsourcing",
    "type": "SubSubTrack",
    "children": [

    ],
    "parent": [
      1525338741116
    ]
  },
  {
    "identifier": 1525338741124,
    "value": "Robotic Process Automation",
    "type": "SubSubTrack",
    "children": [

    ],
    "parent": [
      1525338741116
    ]
  },
  {
    "identifier": 1525338741125,
    "value": "Sales and Fulfilment",
    "type": "SubSubTrack",
    "children": [
    ],
    "parent": [
      1525338741116
    ]
  },
  {
    "identifier": 1525338741126,
    "value": "Sourcing and Procurement",
    "type": "SubSubTrack",
    "children": [
    ],
    "parent": [
      1525338741116
    ]
  },
  {
    "identifier": 1525338741116,
    "value": "Infosys BPM",
    "type": "SubTrack",
    "children": [
      1525338741117,
      1525338741118,
      1525338741119,
      1525338741120,
      1525338741121,
      1525338741122,
      1525338741123,
      1525338741124,
      1525338741125,
      1525338741126
    ],
    "parent": [
      1525338741082
    ]
  },
  {
    "identifier": 1525338741128,
    "value": "Digital Sales Experience",
    "type": "SubSubTrack",
    "children": [
    ],
    "parent": [
      1525338741127
    ]
  },
  {
    "identifier": 1525338741130,
    "value": "Digital Transformation Strategy and Maturity Modeling",
    "type": "SubSubTrack",
    "children": [
    ],
    "parent": [
      1525338741127
    ]
  },
  {
    "identifier": 1525338741131,
    "value": "Organizational Change Management",
    "type": "SubSubTrack",
    "children": [
    ],
    "parent": [
      1525338741127
    ]
  },
  {
    "identifier": 1525338741132,
    "value": "S/4 HANA Migration Assessment",
    "type": "SubSubTrack",
    "children": [
    ],
    "parent": [
      1525338741127
    ]
  },
  {
    "identifier": 1525338741133,
    "value": "Cloud Computing  Strategy and Execution",
    "type": "SubSubTrack",
    "children": [
    ],
    "parent": [
      1525338741127
    ]
  },
  {
    "identifier": 1525338741134,
    "value": "Connnecting with the Consumer  Enterprise Insights Program",
    "type": "SubSubTrack",
    "children": [
    ],
    "parent": [
      1525338741127
    ]
  },
  {
    "identifier": 1525338741135,
    "value": "HR Transformation  SAP Success Factors",
    "type": "SubSubTrack",
    "children": [
    ],
    "parent": [
      1525338741127
    ]
  },
  {
    "identifier": 1525338741136,
    "value": "Integrated Business Planning",
    "type": "SubSubTrack",
    "children": [
    ],
    "parent": [
      1525338741127
    ]
  },
  {
    "identifier": 1525338741137,
    "value": "Multi-Speed IT Delivery",
    "type": "SubSubTrack",
    "children": [
    ],
    "parent": [
      1525338741127
    ]
  },
  {
    "identifier": 1525338741138,
    "value": "Supply Chain  Contract Manufacturing",
    "type": "SubSubTrack",
    "children": [
    ],
    "parent": [
      1525338741127
    ]
  },
  {
    "identifier": 1525338741139,
    "value": "Supply Chain  On-Time Delivery & Product Optimization",
    "type": "SubSubTrack",
    "children": [
    ],
    "parent": [
      1525338741127
    ]
  },
  {
    "identifier": 1525338741127,
    "value": "Infosys Consulting",
    "type": "SubTrack",
    "children": [
      1525338741128,
      1525338741130,
      1525338741131,
      1525338741132,
      1525338741133,
      1525338741134,
      1525338741135,
      1525338741136,
      1525338741137,
      1525338741138,
      1525338741139
    ],
    "parent": [
      1525338741082
    ]
  },
  {
    "identifier": 1525338741141,
    "value": "Autonomous Testing for SAP",
    "type": "SubSubTrack",
    "children": [
    ],
    "parent": [
      1525338741140
    ]
  },
  {
    "identifier": 1525338741143,
    "value": "RDx for Salesforce",
    "type": "SubSubTrack",
    "children": [
    ],
    "parent": [
      1525338741140
    ]
  },
  {
    "identifier": 1525338741144,
    "value": "Release Dynamix (RDx)",
    "type": "SubSubTrack",
    "children": [
    ],
    "parent": [
      1525338741140
    ]
  },
  {
    "identifier": 1525338741145,
    "value": "Test Center",
    "type": "SubSubTrack",
    "children": [
    ],
    "parent": [
      1525338741140
    ]
  },
  {
    "identifier": 1525338741140,
    "value": "Panaya",
    "type": "SubTrack",
    "children": [
      1525338741141,
      1525338741143,
      1525338741144,
      1525338741145
    ],
    "parent": [
      1525338741082
    ]
  },
  {
    "identifier": 1525338741147,
    "value": "Skava Commerce",
    "type": "SubSubTrack",
    "children": [
    ],
    "parent": [
      1525338741146
    ]
  },
  {
    "identifier": 1525338741146,
    "value": "Skava",
    "type": "SubTrack",
    "children": [
      1525338741147
    ],
    "parent": [
      1525338741082
    ]
  },
  {
    "identifier": 1525338741082,
    "value": "Products and Subsidaries",
    "type": "Track",
    "children": [
      1525338741083,
      1525338741093,
      1525338741116,
      1525338741127,
      1525338741140,
      1525338741146
    ],
    "parent": [
      1525338741000
    ]
  },
  {
    "identifier": 1525957676931,
    "value": "Assure",
    "type": "Track",
    "children": [
    ],
    "parent": [
      1525957676930
    ]
  },
  {
    "identifier": 1525957676932,
    "value": "Accelerate",
    "type": "Track",
    "children": [
    ],
    "parent": [
      1525957676930
    ]
  },
  {
    "identifier": 1525957676933,
    "value": "Innovate",
    "type": "Track",
    "children": [
    ],
    "parent": [
      1525957676930
    ]
  },
  {
    "identifier": 1525957676934,
    "value": "Insight",
    "type": "Track",
    "children": [
    ],
    "parent": [
      1525957676930
    ]
  },
  {
    "identifier": 1525957676935,
    "value": "Experience",
    "type": "Track",
    "children": [
    ],
    "parent": [
      1525957676930
    ]
  },
  {
    "identifier": 1525957676930,
    "value": "Navigate Your Next - Themes",
    "type": "Category",
    "children": [
      1525957676931,
      1525957676932,
      1525957676933,
      1525957676934,
      1525957676935
    ],
    "parent": [
      1525338740921
    ]
  },
  {
    "identifier": 1525338741000,
    "value": "Marketing",
    "type": "Category",
    "children": [
      1525338741001,
      1525338741004,
      1525338741044,
      1525338741082
    ],
    "parent": [
      1525338740921
    ]
  },
  {
    "identifier": 1525338740921,
    "value": "Catalog",
    "type": "Catalog",
    "children": [
      1525338740922,
      1525338740953,
      1525338740972,
      1525757739680,
      1525338740987,
      1525338741000,
      1525957676930
    ],
    "parent": [
      1525338740920
    ]
  },
  {
    "identifier": 1525338741150,
    "value": "API Economy",
    "type": "NewServices",
    "children": [
    ],
    "parent": [
      1525338741149
    ]
  },
  {
    "identifier": 1525338741151,
    "value": "Business Process Management (Pega)",
    "type": "NewServices",
    "children": [
    ],
    "parent": [
      1525338741149
    ]
  },
  {
    "identifier": 1525338741149,
    "value": "BPM and APIEconomy",
    "type": "NewServicesTheme",
    "children": [
      1525338741150,
      1525338741151
    ],
    "parent": [
      1525338741148
    ]
  },
  {
    "identifier": 1525338741153,
    "value": "Oracle Cloud Ecosystem",
    "type": "NewServices",
    "children": [
    ],
    "parent": [
      1525338741152
    ]
  },
  {
    "identifier": 1525338741154,
    "value": "Public Cloud workload migration (AWS + Azure)",
    "type": "NewServices",
    "children": [
    ],
    "parent": [
      1525338741152
    ]
  },
  {
    "identifier": 1525338741152,
    "value": "Cloud Infra Ecosystem",
    "type": "NewServicesTheme",
    "children": [
      1525338741153,
      1525338741154
    ],
    "parent": [
      1525338741148
    ]
  },
  {
    "identifier": 1525338741156,
    "value": "Cyber Security",
    "type": "NewServices",
    "children": [
    ],
    "parent": [
      1525338741155
    ]
  },
  {
    "identifier": 1525338741155,
    "value": "Cyber Security",
    "type": "NewServicesTheme",
    "children": [
      1525338741156
    ],
    "parent": [
      1525338741148
    ]
  },
  {
    "identifier": 1525338741158,
    "value": "Big Data and Analytics",
    "type": "NewServices",
    "children": [
    ],
    "parent": [
      1525338741157
    ]
  },
  {
    "identifier": 1525338741159,
    "value": "Data Monetization",
    "type": "NewServices",
    "children": [
    ],
    "parent": [
      1525338741157
    ]
  },
  {
    "identifier": 1525338741157,
    "value": "Data Analytics",
    "type": "NewServicesTheme",
    "children": [
      1525338741158,
      1525338741159
    ],
    "parent": [
      1525338741148
    ]
  },
  {
    "identifier": 1525338741161,
    "value": "Digital Factory/ADS",
    "type": "NewServices",
    "children": [
    ],
    "parent": [
      1525338741160
    ]
  },
  {
    "identifier": 1525338741160,
    "value": "Digital Factory",
    "type": "NewServicesTheme",
    "children": [
      1525338741161
    ],
    "parent": [
      1525338741148
    ]
  },
  {
    "identifier": 1525338741163,
    "value": "Internet of Things",
    "type": "NewServices",
    "children": [
    ],
    "parent": [
      1525338741162
    ]
  },
  {
    "identifier": 1525338741162,
    "value": "Internet of Things",
    "type": "NewServicesTheme",
    "children": [
      1525338741163
    ],
    "parent": [
      1525338741148
    ]
  },
  {
    "identifier": 1525338741165,
    "value": "BI Modernization",
    "type": "NewServices",
    "children": [
    ],
    "parent": [
      1525338741164
    ]
  },
  {
    "identifier": 1525338741166,
    "value": "DevOps and Agile adoption in the enterprise",
    "type": "NewServices",
    "children": [
    ],
    "parent": [
      1525338741164
    ]
  },
  {
    "identifier": 1525338741167,
    "value": "Mainframe Modernization",
    "type": "NewServices",
    "children": [
    ],
    "parent": [
      1525338741164
    ]
  },
  {
    "identifier": 1525338741168,
    "value": "Open Source Development and Migration",
    "type": "NewServices",
    "children": [
    ],
    "parent": [
      1525338741164
    ]
  },
  {
    "identifier": 1525338741169,
    "value": "Product Cost Optimization",
    "type": "NewServices",
    "children": [
    ],
    "parent": [
      1525338741164
    ]
  },
  {
    "identifier": 1525338741170,
    "value": "SDN - Software Defined Networks",
    "type": "NewServices",
    "children": [
    ],
    "parent": [
      1525338741164
    ]
  },
  {
    "identifier": 1525338741171,
    "value": "Workload Transformation for the Cloud",
    "type": "NewServices",
    "children": [
    ],
    "parent": [
      1525338741164
    ]
  },
  {
    "identifier": 1525338741164,
    "value": "Modernization",
    "type": "NewServicesTheme",
    "children": [
      1525338741165,
      1525338741166,
      1525338741167,
      1525338741168,
      1525338741169,
      1525338741170,
      1525338741171
    ],
    "parent": [
      1525338741148
    ]
  },
  {
    "identifier": 1525338741173,
    "value": "ServiceNow ESM Cafe",
    "type": "NewServices",
    "children": [
    ],
    "parent": [
      1525338741172
    ]
  },
  {
    "identifier": 1525338741172,
    "value": "ServiceNow ESM Cafe",
    "type": "NewServicesTheme",
    "children": [
      1525338741173
    ],
    "parent": [
      1525338741148
    ]
  },
  {
    "identifier": 1525338741175,
    "value": "Big Data Testing",
    "type": "NewServices",
    "children": [
    ],
    "parent": [
      1525338741174
    ]
  },
  {
    "identifier": 1525338741176,
    "value": "Mobility Testing",
    "type": "NewServices",
    "children": [
    ],
    "parent": [
      1525338741174
    ]
  },
  {
    "identifier": 1525338741174,
    "value": "Specialized Validation Services",
    "type": "NewSe rvicesTheme",
    "children": [
      1525338741175,
      1525338741176
    ],
    "parent": [
      1525338741148
    ]
  },
  {
    "identifier": 1525338741178,
    "value": "HANA BI Migration and Simplification",
    "type": "NewServices",
    "children": [
    ],
    "parent": [
      1525338741177
    ]
  },
  {
    "identifier": 1525338741179,
    "value": "HCM Cloud - SuccessFactors",
    "type": "NewServices",
    "children": [
    ],
    "parent": [
      1525338741177
    ]
  },
  {
    "identifier": 1525338741180,
    "value": "MS Dynamics - CRM",
    "type": "NewServices",
    "children": [
    ],
    "parent": [
      1525338741177
    ]
  },
  {
    "identifier": 1525338741181,
    "value": "Oracle Edge",
    "type": "NewServices",
    "children": [
    ],
    "parent": [
      1525338741177
    ]
  },
  {
    "identifier": 1525338741182,
    "value": "Oracle Industry solutions/Vertical Stacks",
    "type": "NewServices",
    "children": [
    ],
    "parent": [
      1525338741177
    ]
  },
  {
    "identifier": 1525338741183,
    "value": "S/4 HANA Adoption and Landscape Transformation",
    "type": "NewServices",
    "children": [
    ],
    "parent": [
      1525338741177
    ]
  },
  {
    "identifier": 1525338741184,
    "value": "Salesforce.com / Net Suite",
    "type": "NewServices",
    "children": [
    ],
    "parent": [
      1525338741177
    ]
  },
  {
    "identifier": 1525338741185,
    "value": "UX Transformation - SAP Fiori",
    "type": "NewServices",
    "children": [
    ],
    "parent": [
      1525338741177
    ]
  },
  {
    "identifier": 1525338741177,
    "value": "Strategic Cloud Apps",
    "type": "NewServicesTheme",
    "children": [
      1525338741178,
      1525338741179,
      1525338741180,
      1525338741181,
      1525338741182,
      1525338741183,
      1525338741184,
      1525338741185
    ],
    "parent": [
      1525338741148
    ]
  },
  {
    "identifier": 1525338741148,
    "value": "NewServicesTheme",
    "type": "Catalog",
    "children": [
      1525338741149,
      1525338741152,
      1525338741155,
      1525338741157,
      1525338741160,
      1525338741162,
      1525338741164,
      1525338741172,
      1525338741174,
      1525338741177
    ],
    "parent": [
      1525338740920
    ]
  },
  {
    "identifier": 1525338740920,
    "value": "Category",
    "type": "",
    "children": [
      1525338740921,
      1525338741148
    ],
    "parent": [
    ]
  },
  {
    "identifier": 1526035641472,
    "value": "Client Stories",
    "type": "Track",
    "children": [
    ],
    "parent": [
      1525338741000
    ]
  }
]
